havenpy/__init__.py
havenpy/interceptor.py
havenpy/run.py
havenpy/pb/__init__.py
havenpy/pb/manager_pb2.py
havenpy/pb/manager_pb2_grpc.py
havenpy-0.2.0.dist-info/METADATA
havenpy-0.2.0.dist-info/WHEEL
havenpy-0.2.0.dist-info/top_level.txt
havenpy-0.2.0.dist-info/RECORD
