Metadata-Version: 2.1
Name: havenpy
Version: 0.2.0
Summary: Haven SDK
Author: Haven Technologies Inc.
Author-email: hello@havenllm.com
Requires-Dist: grpcio (==1.54.2)
Requires-Dist: protobuf (==4.23.3)
